{
	"name": "pl_remove_old_files",
	"properties": {
		"activities": [
			{
				"name": "Get Metadata1",
				"type": "GetMetadata",
				"dependsOn": [],
				"policy": {
					"timeout": "0.12:00:00",
					"retry": 0,
					"retryIntervalInSeconds": 30,
					"secureOutput": false,
					"secureInput": false
				},
				"userProperties": [],
				"typeProperties": {
					"dataset": {
						"referenceName": "ds_copy_file_count",
						"type": "DatasetReference"
					},
					"fieldList": [
						"childItems"
					],
					"storeSettings": {
						"type": "AzureBlobFSReadSettings",
						"enablePartitionDiscovery": false
					},
					"formatSettings": {
						"type": "DelimitedTextReadSettings"
					}
				}
			},
			{
				"name": "ForEach1",
				"type": "ForEach",
				"dependsOn": [
					{
						"activity": "Get Metadata1",
						"dependencyConditions": [
							"Succeeded"
						]
					}
				],
				"userProperties": [],
				"typeProperties": {
					"items": {
						"value": "@activity('Get Metadata1').output.childItems",
						"type": "Expression"
					},
					"batchCount": 4,
					"activities": [
						{
							"name": "Get Metadata Inside ForEach",
							"type": "GetMetadata",
							"dependsOn": [],
							"policy": {
								"timeout": "0.12:00:00",
								"retry": 0,
								"retryIntervalInSeconds": 30,
								"secureOutput": false,
								"secureInput": false
							},
							"userProperties": [],
							"typeProperties": {
								"dataset": {
									"referenceName": "ds_copy_file_count",
									"type": "DatasetReference"
								},
								"fieldList": [
									{
										"value": "@item().name",
										"type": "Expression"
									}
								],
								"storeSettings": {
									"type": "AzureBlobFSReadSettings",
									"enablePartitionDiscovery": false
								},
								"formatSettings": {
									"type": "DelimitedTextReadSettings"
								}
							}
						},
						{
							"name": "If Condition1",
							"type": "IfCondition",
							"dependsOn": [
								{
									"activity": "Get Metadata Inside ForEach",
									"dependencyConditions": [
										"Succeeded"
									]
								}
							],
							"userProperties": [],
							"typeProperties": {
								"expression": {
									"value": "@greaterOrEquals(activity('Get Metadata Inside ForEach').output.lastModified, addMinutes(utcNow(), -10))",
									"type": "Expression"
								},
								"ifTrueActivities": [
									{
										"name": "Delete File",
										"type": "Delete",
										"state": "Inactive",
										"onInactiveMarkAs": "Succeeded",
										"dependsOn": [],
										"policy": {
											"timeout": "0.12:00:00",
											"retry": 0,
											"retryIntervalInSeconds": 30,
											"secureOutput": false,
											"secureInput": false
										},
										"userProperties": [],
										"typeProperties": {
											"enableLogging": true
										}
									},
									{
										"name": "Copy data1",
										"type": "Copy",
										"dependsOn": [],
										"policy": {
											"timeout": "0.12:00:00",
											"retry": 0,
											"retryIntervalInSeconds": 30,
											"secureOutput": false,
											"secureInput": false
										},
										"userProperties": [],
										"typeProperties": {
											"source": {
												"type": "DelimitedTextSource",
												"storeSettings": {
													"type": "AzureBlobFSReadSettings",
													"recursive": true,
													"enablePartitionDiscovery": false
												},
												"formatSettings": {
													"type": "DelimitedTextReadSettings"
												}
											},
											"sink": {
												"type": "DelimitedTextSink",
												"storeSettings": {
													"type": "AzureBlobFSWriteSettings"
												},
												"formatSettings": {
													"type": "DelimitedTextWriteSettings",
													"quoteAllText": true,
													"fileExtension": ".txt"
												}
											},
											"enableStaging": false,
											"translator": {
												"type": "TabularTranslator",
												"typeConversion": true,
												"typeConversionSettings": {
													"allowDataTruncation": true,
													"treatBooleanAsNumber": false
												}
											}
										},
										"inputs": [
											{
												"referenceName": "ds_lookup_act",
												"type": "DatasetReference",
												"parameters": {
													"file_name": {
														"value": "@item().name",
														"type": "Expression"
													}
												}
											}
										],
										"outputs": [
											{
												"referenceName": "ds_sink_delete",
												"type": "DatasetReference"
											}
										]
									}
								]
							}
						}
					]
				}
			}
		],
		"folder": {
			"name": "file_cleanup_pipelines"
		},
		"annotations": []
	}
}